[
    {
        "title": "a new note",
        "text": "stuff\nmore stuff\nmore stuff\nalot \nof\neffing\nstuff",
        "note_id": "8bd2"
    },
    {
        "title": "a new note",
        "text": "stuff\nmore stuff\nmore stuff\nalot \nof\neffing\nstuff",
        "note_id": "f6a2"
    },
    {
        "title": "a new note",
        "text": "stuff\nmore stuff\nmore stuff\nalot \nof\neffing\nstuff",
        "note_id": "07dd"
    },
    {
        "title": "a new note",
        "text": "stuff\nmore stuff\nmore stuff\nalot \nof\neffing\nstuff",
        "note_id": "3251"
    },
    {
        "title": "i love notes",
        "text": "syke\nlol\nxd\n",
        "note_id": "197a"
    },
    {
        "title": "i love notes",
        "text": "syke\nlol\nxd\n",
        "note_id": "0781"
    }
]